{"id": "i_n114068", "name": "Delirious Divinity of the Sacred Lord", "rarity": 5, "description": "Weapon Ascension Material.  The Sacred Lord of the ineffable city often murmured non-human languages inhis dreams, and when he beheld himself in the mirror, he saw how the singlepupil that was visible through his mask was gradually becoming vertical. Thisonly served to further fuel his growing hatred for the dragons.  It is said that when the scarlet-eyed youth burned down that city above acity, submerged in shadow as it was, he witnessed a half-human figure beforethe royal hall who had been driven mad. As if tearing off its very face, itripped away at its indelible divine visage, revealing gaping holes that werefearsomely draconic.  Consumed by the golden flames it spewed, the disfigured form of that derangedsoul fell from a great height into the pitch-black mire below. Forsaken byall, thus was the tragic end that this delusional outcast is said to have met.", "material_type": "PrimaryAscensionMaterial", "weekdays": ["Wednesday", "Thursday", "Sunday"]}